AgroMetEquations/.gitignore
AgroMetEquations/__init__.py
AgroMetEquations/auxiliary.py
AgroMetEquations/config.py
AgroMetEquations/docs/Evapotranspiration_Equation.pdf
AgroMetEquations/evapotranspiration_equations.py
AgroMetEquations/thornthwaite_mather_1955_waterbalance.py
agro_met_equations_dynalogic-2.0.2.dist-info/LICENSE
agro_met_equations_dynalogic-2.0.2.dist-info/WHEEL
agro_met_equations_dynalogic-2.0.2.dist-info/METADATA
agro_met_equations_dynalogic-2.0.2.dist-info/RECORD
