Metadata-Version: 2.1
Name: agro-met-equations-dynalogic
Version: 2.0.2
Summary: Library for agrometeorological calculation like evapotranspiration, water balance, degree days, water balance ...
Home-page: https://github.com/dynalogic-agtech/dynalogic-agro-met-equations-pkg
License: BSD 3-Clause
Keywords: Atmospheric Science,Agricultural Meteorology
Author: Bruno Ducraux
Author-email: bducraux@dynalogic.net
Requires-Python: >=3.8
Classifier: License :: Other/Proprietary License
Classifier: Programming Language :: Python :: 3
Classifier: Programming Language :: Python :: 3.10
Classifier: Programming Language :: Python :: 3.8
Classifier: Programming Language :: Python :: 3.9
Project-URL: Repository, https://github.com/dynalogic-agtech/dynalogic-agro-met-equations-pkg
